animalwellsave/__init__.py
animalwellsave/cli.py
animalwellsave/datafile.py
animalwellsave/savegame.py
animalwellsave-1.2.2.dist-info/LICENSE.txt
animalwellsave-1.2.2.dist-info/METADATA
animalwellsave-1.2.2.dist-info/WHEEL
animalwellsave-1.2.2.dist-info/entry_points.txt
animalwellsave-1.2.2.dist-info/top_level.txt
animalwellsave-1.2.2.dist-info/RECORD
