Metadata-Version: 2.2
Name: animalwellsave
Version: 1.2.2
Summary: Animal Well CLI Savegame Editor/Library
Author-email: CJ Kucera <cj@apocalyptech.com>
License:                     GNU GENERAL PUBLIC LICENSE
Project-URL: Repository, https://github.com/apocalyptech/animalwellsave
Project-URL: Issues, https://github.com/apocalyptech/animalwellsave/issues
Keywords: animalwell,animal well,save editor
Classifier: Development Status :: 5 - Production/Stable
Classifier: Environment :: Console
Classifier: Intended Audience :: End Users/Desktop
Classifier: Intended Audience :: Developers
Classifier: License :: OSI Approved :: GNU General Public License v3 or later (GPLv3+)
Classifier: Natural Language :: English
Classifier: Programming Language :: Python
Classifier: Programming Language :: Python :: 3
Classifier: Programming Language :: Python :: 3.10
Classifier: Programming Language :: Python :: 3.11
Classifier: Programming Language :: Python :: 3.12
Classifier: Programming Language :: Python :: 3.13
Requires-Python: >=3.10
License-File: LICENSE.txt
Provides-Extra: images
Requires-Dist: pillow; extra == "images"
